collection/__init__.py
collection/collection.py
pycollection/__init__.py
pycollection/collection.py
src/__init__.py
src/collection.py
pycollection-1.0.6.dist-info/LICENSE
pycollection-1.0.6.dist-info/METADATA
pycollection-1.0.6.dist-info/WHEEL
pycollection-1.0.6.dist-info/top_level.txt
pycollection-1.0.6.dist-info/RECORD
