Metadata-Version: 2.1
Name: pycollection
Version: 1.0.6
Summary: Collection iterator over classes
Home-page: UNKNOWN
Author: Cristian Guzmán
Author-email: <cristian.guzman.contacto@gmail.com>
License: UNKNOWN
Keywords: python,collection,laravel,iterator,pycollection
Platform: UNKNOWN
Requires-Dist: typing
